testmsg/__init__.py
testmsg/__main__.py
testmsg/mysmtp.py
testmsg-0.0.24.dist-info/METADATA
testmsg-0.0.24.dist-info/WHEEL
testmsg-0.0.24.dist-info/entry_points.txt
testmsg-0.0.24.dist-info/licenses/LICENSE
testmsg-0.0.24.dist-info/RECORD
