Metadata-Version: 2.4
Name: testmsg
Version: 0.0.24
Summary: Simple CLI tool to generate/send valid RFC822 email messages (with DKIM optionally)
Project-URL: Homepage, https://github.com/yaroslaff/testmsg
Project-URL: Issues, https://github.com/yaroslaff/testmsg/issues
Author-email: Yaroslav Polyakov <yaroslaff@gmail.com>
License-File: LICENSE
Classifier: License :: OSI Approved :: MIT License
Classifier: Operating System :: OS Independent
Classifier: Programming Language :: Python :: 3
Requires-Python: >=3.7
Requires-Dist: dkimpy
Requires-Dist: python-dotenv
Requires-Dist: rich
